MANIFEST.in
README.md
setup.py
gender_neutral_name/__init__.py
gender_neutral_name/provider.py
gender_neutral_name.egg-info/PKG-INFO
gender_neutral_name.egg-info/SOURCES.txt
gender_neutral_name.egg-info/dependency_links.txt
gender_neutral_name.egg-info/requires.txt
gender_neutral_name.egg-info/top_level.txt
gender_neutral_name.egg-info/zip-safe
gender_neutral_name/data/adjective.json
gender_neutral_name/data/names.json